Workbook

Sheet Pricing
A1: CONDO ASSISTANT — PRICING (per unit / month)
A3: Band | B3: Units | C3: Condo Assistant | D3: Auto Email | E3: Bundle (Both) | F3: Bundle Disc.
A4: Base | B4: 1–2 units | C4: 15 | D4: 15 | E4: 25 | F4: =1-E4/$E$4
A5: Tier 1 | B5: 3–9 units | C5: 13.25 | D5: 13.25 | E5: 22 | F5: =1-E5/$E$4
A6: Tier 2 | B6: 10+ units | C6: 12 | D6: 12 | E6: 20 | F6: =1-E6/$E$4
A8: MONTHLY CAP: $500 per client (up to 100 units). 100+ units = custom quote.
A9: The cap smooths the curve: a client's bill rises with units, then plateaus at $500 — it never drops as they add units. Big clients get a deep effective discount (75 units ≈ $6.67/unit).

Sheet Revenue Model
A1: REVENUE MODEL — at full penetration
A3: Bundle Adoption % | B3: 0.65
A4: Single-Product % | B4: =1-B3
A5: Monthly Cap / Client ($) | B5: 500
A7: Band | B7: # Clients | C7: Avg Units | D7: Total Units | E7: Bundle $/u | F7: Single $/u | G7: Blended $/u | H7: Bill/Client | I7: Monthly Rev | J7: Annual Rev
A8: 1–2 units | B8: 4000 | C8: 1.5 | D8: =B8*C8 | E8: =Pricing!E4 | F8: =Pricing!C4 | G8: =$B$3*E8+$B$4*F8 | H8: =MIN(C8*G8,$B$5) | I8: =B8*H8 | J8: =I8*12
A9: 3–9 units | B9: 500 | C9: 5 | D9: =B9*C9 | E9: =Pricing!E5 | F9: =Pricing!C5 | G9: =$B$3*E9+$B$4*F9 | H9: =MIN(C9*G9,$B$5) | I9: =B9*H9 | J9: =I9*12
A10: 10–19 units | B10: 300 | C10: 13 | D10: =B10*C10 | E10: =Pricing!E6 | F10: =Pricing!C6 | G10: =$B$3*E10+$B$4*F10 | H10: =MIN(C10*G10,$B$5) | I10: =B10*H10 | J10: =I10*12
A11: 20–49 units | B11: 200 | C11: 30 | D11: =B11*C11 | E11: =Pricing!E6 | F11: =Pricing!C6 | G11: =$B$3*E11+$B$4*F11 | H11: =MIN(C11*G11,$B$5) | I11: =B11*H11 | J11: =I11*12
A12: 50–100 units | B12: 50 | C12: 75 | D12: =B12*C12 | E12: =Pricing!E6 | F12: =Pricing!C6 | G12: =$B$3*E12+$B$4*F12 | H12: =MIN(C12*G12,$B$5) | I12: =B12*H12 | J12: =I12*12
A13: TOTAL | B13: =SUM(B8:B12) | D13: =SUM(D8:D12) | I13: =SUM(I8:I12) | J13: =SUM(J8:J12)
A15: ARR at full penetration → | J15: =J13

Sheet Unit Economics
A1: UNIT ECONOMICS (at full scale)
A3: Avg Revenue / Unit / Month | B3: ='Revenue Model'!I13/'Revenue Model'!D13
A4: COGS / Unit / Month (from COGS Breakdown) | B4: ='COGS Breakdown'!B10
A5: Stripe Fee (% of revenue) | B5: 0.035
A6: Gross Profit / Unit / Month | B6: =B3-B4-B3*B5
A7: Gross Margin % | B7: =B6/B3
A9: PER CLIENT
A10: Avg Units / Client | B10: ='Revenue Model'!D13/'Revenue Model'!B13
A11: Avg Revenue / Client / Month | B11: ='Revenue Model'!I13/'Revenue Model'!B13
A12: Gross Profit / Client / Month | B12: =B6*B10
A14: CAC / LTV
A15: CAC | B15: 150
A16: Monthly Churn % | B16: 0.03
A17: Avg Customer Lifetime (months) | B17: =1/B16
A18: LTV (gross profit) | B18: =B12*B17
A19: LTV : CAC | B19: =B18/B15
A20: CAC Payback (months) | B20: =B15/B12

Sheet Rollout Ramp
A1: ROLLOUT RAMP
A3: Year | B3: Clients | C3: % Target | D3: Est. ARR | E3: Phase / Focus
A4: Year 1 | B4: 500 | C4: =B4/5050 | D4: =B4*('Revenue Model'!J13/'Revenue Model'!B13) | E4: Pilot — small owners via WPM referrals + CO STR groups (near-zero CAC)
A5: Year 2 | B5: 2000 | C5: =B5/5050 | D5: =B5*('Revenue Model'!J13/'Revenue Model'!B13) | E5: Land large PM companies (Option C) — they refer & credential the small owners
A6: Year 3 | B6: 5050 | C6: =B6/5050 | D6: =B6*('Revenue Model'!J13/'Revenue Model'!B13) | E6: Full penetration — paid acquisition + referral flywheel (Option B)

Sheet Assumptions & Notes
A1: PRICING
A2: Products | B2: Condo Assistant $15/unit · Auto Email $15/unit · Bundle (both) $25/unit (base)
A3: Volume tiers (bundle) | B3: 1–2 units $25 · 3–9 $22 · 10+ $20 per unit
A4: Monthly cap | B4: $500/client up to 100 units. This smooths the cliff — the bill plateaus at $500, never drops. 100+ = custom.
A5: Effective enterprise discount | B5: A 75-unit client at the $500 cap pays ≈$6.67/unit (73% off) — deep discount to land large managers.
A7: STRATEGY
A8: Priority | B8: Under-5-unit owners — most profitable per unit, biggest segment (4,000 of 5,050 clients).
A9: Large managers = channel | B9: Big PM companies (20–100 units) are priced aggressively (capped) because their adoption + referrals make the small, profitable owners easier & cheaper to land.
A11: CLIENT DISTRIBUTION (your numbers)
A12: 1–2 units | B12: 4,000 clients
A13: 3–9 units | B13: 500 · 10–19: 300 · 20–49: 200 · 50–100: 50 (seeded "rest") = 5,050 total
A14: Avg units/client | B14: Illustrative (1.5 / 5 / 13 / 30 / 75) — refine with real data
A16: UNIT ECONOMICS
A17: COGS/unit/mo | B17: $3 placeholder (Claude API + hosting + Resend)
A18: Stripe / CAC / churn | B18: ~3.5% / $150 / 3% monthly — illustrative
A20: All numbers illustrative | B20: Planning model for Alex — this is a first-pass guess. Replace estimates with real data as it comes in.

Sheet COGS Breakdown
A1: COGS BREAKDOWN (per unit / month)
A2: Cost Component | B2: $ / Unit / Mo | C2: Basis
A3: Guest chat AI (Claude Haiku 4.5) | B3: 0.45 | C3: ~90 questions/mo (6 res × 15 Q), ~4.2K tokens each @ $1/$5 per M
A4: Auto Email AI (Claude Haiku 4.5) | B4: 0.68 | C4: ~100 AI replies/mo (200-email thread), ~5.35K tokens each
A5: Hosting (Vercel + Supabase, amortized) | B5: 1 | C5: App hosting + Postgres/pgvector, spread per unit
A6: Email delivery (Resend) | B6: 0.15 | C6: Transactional + auto-reply sends
A7: Embeddings (OpenAI, RAG) | B7: 0.05 | C7: Query embeddings per message (near-zero)
A8: Buffer / overage | B8: 0.67 | C8: Headroom for spikes, Sonnet upgrade, growth
A10: TOTAL COGS / Unit / Month | B10: =SUM(B3:B8)
A12: Model: Claude Haiku 4.5 ($1/M in · $5/M out). Sonnet 5 upgrade ≈ 3× the AI lines. Estimates — calibrate with real prompt sizes via count_tokens.
