Workbook

Sheet Fleet Model
A1: Vehicle | B1: Category | C1: Purchase Price | D1: Down Payment | E1: Amount Financed | F1: APR | G1: Term (yrs) | H1: Annual Loan Pmt | I1: Winter Tires | J1: Summer Tires | K1: Roof Box (Thule) | L1: 12V AC Fridge | M1: Camping Pack (opt) | N1: Total Kit | O1: Kit Amort/Yr | P1: Tire Refresh/Yr | Q1: Insurance/Yr | R1: Maintenance/Yr | S1: Misc/Yr | T1: Rate/Day | U1: Days/Mo | V1: Rental Days/Yr | W1: Rental Rev/Yr | X1: Camp $/Day | Y1: Camp Attach % | Z1: Camp Rev/Yr | AA1: Gross Rev/Yr | AB1: Merchant Fee 3% | AC1: Net/Yr During Loan | AD1: Net/Yr Post-Loan | AE1: Residual % | AF1: Residual $ (5yr) | AG1: Avg Miles/Rental Day | AH1: Total Miles (5yr) | AI1: 5-Yr Cumulative Profit
A2: Porsche 911 Carrera Cabriolet | B2: Exotic / Sports | C2: 60000 | D2: 0 | E2: =C2-D2 | F2: 0.06 | G2: 5 | H2: =PMT(F2/12,G2*12,-E2)*12 | I2: 1600 | J2: 1400 | K2: 0 | L2: 0 | M2: 0 | N2: =SUM(I2:M2) | O2: =N2/G2 | P2: =(I2+J2)/3 | Q2: 2500 | R2: 5000 | S2: 1500 | T2: 335 | U2: 13 | V2: =U2*12 | W2: =T2*V2 | X2: 0 | Y2: 0 | Z2: =V2*Y2*X2 | AA2: =W2+Z2 | AB2: =AA2*0.03 | AC2: =AA2-AB2-H2-O2-P2-Q2-R2-S2 | AD2: =AA2-AB2-P2-Q2-R2-S2 | AE2: 0.85 | AF2: =C2*AE2 | AG2: 100 | AH2: =V2*AG2*5 | AI2: =AC2*5+AF2-D2
A3: Porsche 356 Spyder (vintage) | B3: Classic / Exotic | C3: 45000 | D3: 0 | E3: =C3-D3 | F3: 0.06 | G3: 5 | H3: =PMT(F3/12,G3*12,-E3)*12 | I3: 1600 | J3: 1400 | K3: 0 | L3: 0 | M3: 0 | N3: =SUM(I3:M3) | O3: =N3/G3 | P3: =(I3+J3)/3 | Q3: 2500 | R3: 4000 | S3: 1200 | T3: 300 | U3: 8 | V3: =U3*12 | W3: =T3*V3 | X3: 0 | Y3: 0 | Z3: =V3*Y3*X3 | AA3: =W3+Z3 | AB3: =AA3*0.03 | AC3: =AA3-AB3-H3-O3-P3-Q3-R3-S3 | AD3: =AA3-AB3-P3-Q3-R3-S3 | AE3: 1.05 | AF3: =C3*AE3 | AG3: 60 | AH3: =V3*AG3*5 | AI3: =AC3*5+AF3-D3
A4: Toyota 4WD Minivan (Sienna AWD) | B4: Family / Van | C4: 45000 | D4: 0 | E4: =C4-D4 | F4: 0.06 | G4: 5 | H4: =PMT(F4/12,G4*12,-E4)*12 | I4: 1400 | J4: 1000 | K4: 1000 | L4: 900 | M4: 1500 | N4: =SUM(I4:M4) | O4: =N4/G4 | P4: =(I4+J4)/3 | Q4: 1800 | R4: 2500 | S4: 1000 | T4: 150 | U4: 15 | V4: =U4*12 | W4: =T4*V4 | X4: 35 | Y4: 0.25 | Z4: =V4*Y4*X4 | AA4: =W4+Z4 | AB4: =AA4*0.03 | AC4: =AA4-AB4-H4-O4-P4-Q4-R4-S4 | AD4: =AA4-AB4-P4-Q4-R4-S4 | AE4: 0.62 | AF4: =C4*AE4 | AG4: 130 | AH4: =V4*AG4*5 | AI4: =AC4*5+AF4-D4
A5: Mazda Miata (ND) | B5: Sports / Fun | C5: 32000 | D5: 0 | E5: =C5-D5 | F5: 0.06 | G5: 5 | H5: =PMT(F5/12,G5*12,-E5)*12 | I5: 1600 | J5: 1400 | K5: 0 | L5: 0 | M5: 0 | N5: =SUM(I5:M5) | O5: =N5/G5 | P5: =(I5+J5)/3 | Q5: 1800 | R5: 2500 | S5: 1000 | T5: 120 | U5: 12 | V5: =U5*12 | W5: =T5*V5 | X5: 0 | Y5: 0 | Z5: =V5*Y5*X5 | AA5: =W5+Z5 | AB5: =AA5*0.03 | AC5: =AA5-AB5-H5-O5-P5-Q5-R5-S5 | AD5: =AA5-AB5-P5-Q5-R5-S5 | AE5: 0.68 | AF5: =C5*AE5 | AG5: 100 | AH5: =V5*AG5*5 | AI5: =AC5*5+AF5-D5
A6: Chevrolet C8 Corvette | B6: Exotic / Sports | C6: 75000 | D6: 0 | E6: =C6-D6 | F6: 0.06 | G6: 5 | H6: =PMT(F6/12,G6*12,-E6)*12 | I6: 1600 | J6: 1400 | K6: 0 | L6: 0 | M6: 0 | N6: =SUM(I6:M6) | O6: =N6/G6 | P6: =(I6+J6)/3 | Q6: 2500 | R6: 4500 | S6: 1500 | T6: 395 | U6: 12 | V6: =U6*12 | W6: =T6*V6 | X6: 0 | Y6: 0 | Z6: =V6*Y6*X6 | AA6: =W6+Z6 | AB6: =AA6*0.03 | AC6: =AA6-AB6-H6-O6-P6-Q6-R6-S6 | AD6: =AA6-AB6-P6-Q6-R6-S6 | AE6: 0.75 | AF6: =C6*AE6 | AG6: 90 | AH6: =V6*AG6*5 | AI6: =AC6*5+AF6-D6
A7: Land Rover Defender 130 | B7: Luxury Adventure | C7: 60000 | D7: 0 | E7: =C7-D7 | F7: 0.06 | G7: 5 | H7: =PMT(F7/12,G7*12,-E7)*12 | I7: 2200 | J7: 1600 | K7: 1000 | L7: 900 | M7: 1500 | N7: =SUM(I7:M7) | O7: =N7/G7 | P7: =(I7+J7)/3 | Q7: 2200 | R7: 3500 | S7: 1500 | T7: 325 | U7: 15 | V7: =U7*12 | W7: =T7*V7 | X7: 35 | Y7: 0.25 | Z7: =V7*Y7*X7 | AA7: =W7+Z7 | AB7: =AA7*0.03 | AC7: =AA7-AB7-H7-O7-P7-Q7-R7-S7 | AD7: =AA7-AB7-P7-Q7-R7-S7 | AE7: 0.8 | AF7: =C7*AE7 | AG7: 120 | AH7: =V7*AG7*5 | AI7: =AC7*5+AF7-D7
A8: Lotus Emira (V6 auto) | B8: Exotic / Sports | C8: 100000 | D8: 0 | E8: =C8-D8 | F8: 0.06 | G8: 5 | H8: =PMT(F8/12,G8*12,-E8)*12 | I8: 1600 | J8: 1400 | K8: 0 | L8: 0 | M8: 0 | N8: =SUM(I8:M8) | O8: =N8/G8 | P8: =(I8+J8)/3 | Q8: 2800 | R8: 5000 | S8: 1500 | T8: 425 | U8: 10 | V8: =U8*12 | W8: =T8*V8 | X8: 0 | Y8: 0 | Z8: =V8*Y8*X8 | AA8: =W8+Z8 | AB8: =AA8*0.03 | AC8: =AA8-AB8-H8-O8-P8-Q8-R8-S8 | AD8: =AA8-AB8-P8-Q8-R8-S8 | AE8: 0.68 | AF8: =C8*AE8 | AG8: 80 | AH8: =V8*AG8*5 | AI8: =AC8*5+AF8-D8
A9: Chevrolet C7 Corvette | B9: Sports | C9: 55000 | D9: 0 | E9: =C9-D9 | F9: 0.06 | G9: 5 | H9: =PMT(F9/12,G9*12,-E9)*12 | I9: 1600 | J9: 1400 | K9: 0 | L9: 0 | M9: 0 | N9: =SUM(I9:M9) | O9: =N9/G9 | P9: =(I9+J9)/3 | Q9: 2200 | R9: 3500 | S9: 1200 | T9: 275 | U9: 12 | V9: =U9*12 | W9: =T9*V9 | X9: 0 | Y9: 0 | Z9: =V9*Y9*X9 | AA9: =W9+Z9 | AB9: =AA9*0.03 | AC9: =AA9-AB9-H9-O9-P9-Q9-R9-S9 | AD9: =AA9-AB9-P9-Q9-R9-S9 | AE9: 0.62 | AF9: =C9*AE9 | AG9: 100 | AH9: =V9*AG9*5 | AI9: =AC9*5+AF9-D9
A10: Jeep Wrangler | B10: Off-Road | C10: 45000 | D10: 0 | E10: =C10-D10 | F10: 0.06 | G10: 5 | H10: =PMT(F10/12,G10*12,-E10)*12 | I10: 2200 | J10: 1600 | K10: 1000 | L10: 900 | M10: 1500 | N10: =SUM(I10:M10) | O10: =N10/G10 | P10: =(I10+J10)/3 | Q10: 2000 | R10: 3000 | S10: 1200 | T10: 200 | U10: 15 | V10: =U10*12 | W10: =T10*V10 | X10: 35 | Y10: 0.25 | Z10: =V10*Y10*X10 | AA10: =W10+Z10 | AB10: =AA10*0.03 | AC10: =AA10-AB10-H10-O10-P10-Q10-R10-S10 | AD10: =AA10-AB10-P10-Q10-R10-S10 | AE10: 0.68 | AF10: =C10*AE10 | AG10: 130 | AH10: =V10*AG10*5 | AI10: =AC10*5+AF10-D10
A11: Toyota Tacoma | B11: Adventure Truck | C11: 45000 | D11: 0 | E11: =C11-D11 | F11: 0.06 | G11: 5 | H11: =PMT(F11/12,G11*12,-E11)*12 | I11: 2200 | J11: 1600 | K11: 1000 | L11: 900 | M11: 1500 | N11: =SUM(I11:M11) | O11: =N11/G11 | P11: =(I11+J11)/3 | Q11: 2000 | R11: 2800 | S11: 1200 | T11: 185 | U11: 15 | V11: =U11*12 | W11: =T11*V11 | X11: 35 | Y11: 0.25 | Z11: =V11*Y11*X11 | AA11: =W11+Z11 | AB11: =AA11*0.03 | AC11: =AA11-AB11-H11-O11-P11-Q11-R11-S11 | AD11: =AA11-AB11-P11-Q11-R11-S11 | AE11: 0.72 | AF11: =C11*AE11 | AG11: 130 | AH11: =V11*AG11*5 | AI11: =AC11*5+AF11-D11
A12: Toyota Land Cruiser | B12: Premium SUV | C12: 85000 | D12: 0 | E12: =C12-D12 | F12: 0.06 | G12: 5 | H12: =PMT(F12/12,G12*12,-E12)*12 | I12: 2200 | J12: 1600 | K12: 1000 | L12: 900 | M12: 1500 | N12: =SUM(I12:M12) | O12: =N12/G12 | P12: =(I12+J12)/3 | Q12: 2300 | R12: 3500 | S12: 1500 | T12: 350 | U12: 13 | V12: =U12*12 | W12: =T12*V12 | X12: 35 | Y12: 0.25 | Z12: =V12*Y12*X12 | AA12: =W12+Z12 | AB12: =AA12*0.03 | AC12: =AA12-AB12-H12-O12-P12-Q12-R12-S12 | AD12: =AA12-AB12-P12-Q12-R12-S12 | AE12: 0.78 | AF12: =C12*AE12 | AG12: 120 | AH12: =V12*AG12*5 | AI12: =AC12*5+AF12-D12
A13: Lexus GX 550 | B13: Luxury Family SUV | C13: 70000 | D13: 0 | E13: =C13-D13 | F13: 0.06 | G13: 5 | H13: =PMT(F13/12,G13*12,-E13)*12 | I13: 2200 | J13: 1600 | K13: 1000 | L13: 900 | M13: 1500 | N13: =SUM(I13:M13) | O13: =N13/G13 | P13: =(I13+J13)/3 | Q13: 2200 | R13: 3200 | S13: 1500 | T13: 325 | U13: 14 | V13: =U13*12 | W13: =T13*V13 | X13: 35 | Y13: 0.25 | Z13: =V13*Y13*X13 | AA13: =W13+Z13 | AB13: =AA13*0.03 | AC13: =AA13-AB13-H13-O13-P13-Q13-R13-S13 | AD13: =AA13-AB13-P13-Q13-R13-S13 | AE13: 0.7 | AF13: =C13*AE13 | AG13: 120 | AH13: =V13*AG13*5 | AI13: =AC13*5+AF13-D13
... A17: Mercedes R-Class (2012) | B17: Ski / Family Hauler | C17: 10000 | D17: 0 | E17: =C17-D17 | F17: 0.06 | G17: 5 | H17: =PMT(F17/12,G17*12,-E17)*12 | I17: 1400 | J17: 1000 | K17: 1000 | L17: 900 | M17: 1500 | N17: =SUM(I17:M17) | O17: =N17/G17 | P17: =(I17+J17)/3 | Q17: 1500 | R17: 2500 | S17: 1000 | T17: 150 | U17: 12.5 | V17: =U17*12 | W17: =T17*V17 | X17: 35 | Y17: 0.25 | Z17: =V17*Y17*X17 | AA17: =W17+Z17 | AB17: =AA17*0.03 | AC17: =AA17-AB17-H17-O17-P17-Q17-R17-S17 | AD17: =AA17-AB17-P17-Q17-R17-S17 | AE17: 0.6 | AF17: =C17*AE17 | AG17: 130 | AH17: =V17*AG17*5 | AI17: =AC17*5+AF17-D17
A18: FLEET TOTAL | C18: =SUM(C2:C17) | D18: =SUM(D2:D17) | E18: =SUM(E2:E17) | H18: =SUM(H2:H17) | I18: =SUM(I2:I17) | J18: =SUM(J2:J17) | K18: =SUM(K2:K17) | L18: =SUM(L2:L17) | M18: =SUM(M2:M17) | N18: =SUM(N2:N17) | O18: =SUM(O2:O17) | ... S18: =SUM(S2:S17) | V18: =SUM(V2:V17) | W18: =SUM(W2:W17) | Z18: =SUM(Z2:Z17) | AA18: =SUM(AA2:AA17) | AB18: =SUM(AB2:AB17) | AC18: =SUM(AC2:AC17) | AD18: =SUM(AD2:AD17) | AF18: =SUM(AF2:AF17) | AH18: =SUM(AH2:AH17) | AI18: =SUM(AI2:AI17)

Sheet Fleet Summary
A1: FLEET SUMMARY (16 vehicles)
A3: Total Purchase Price | B3: =SUM('Fleet Model'!C2:C17)
A4: Total Vehicle Kit (incl. camping) | B4: =SUM('Fleet Model'!N2:N17)
A5: Total Capital Deployed | B5: =SUM('Fleet Model'!C2:C17)+SUM('Fleet Model'!N2:N17)
A7: Total Rental Revenue / Yr | B7: =SUM('Fleet Model'!W2:W17)
A8: Total Camping Upsell / Yr | B8: =SUM('Fleet Model'!Z2:Z17)
A9: Total Gross Revenue / Yr | B9: =SUM('Fleet Model'!AA2:AA17)
A10: Total Merchant Fees / Yr (3%) | B10: =SUM('Fleet Model'!AB2:AB17)
A11: Total Tire Refresh Reserve / Yr | B11: =SUM('Fleet Model'!P2:P17)
A12: Total Net / Yr — During Loan | B12: =SUM('Fleet Model'!AC2:AC17)
A13: Total Net / Yr — Post-Loan | B13: =SUM('Fleet Model'!AD2:AD17)
A15: Total Residual Value @ 5 Yrs | B15: =SUM('Fleet Model'!AF2:AF17)
A16: Total Fleet Mileage @ 5 Yrs | B16: =SUM('Fleet Model'!AH2:AH17)
A17: Total 5-Yr Cumulative Profit | B17: =SUM('Fleet Model'!AI2:AI17)
A19: Avg Net/Yr per Vehicle (During Loan) | B19: =SUM('Fleet Model'!AC2:AC17)/16
A20: 5-Yr ROI on Capital | B20: =SUM('Fleet Model'!AI2:AI17)/(SUM('Fleet Model'!C2:C17)+SUM('Fleet Model'!N2:N17))

Sheet Assumptions & Notes
A1: GLOBAL ASSUMPTIONS
A2: Financing | B2: 6% APR, 5-yr term, monthly amortization, $0 down (editable per row)
A3: Merchant processing | B3: 3% of gross (own-website booking via Stripe/card — no Turo/platform commission)
A4: Business model | B4: Rent direct through own website. Based in Denver near the I-70 corridor.
A6: VEHICLE KIT (one-time, amortized over 5 yrs)
A7: Sports / exotic | B7: NOW carry tires: winter $1,600 + summer $1,400. No roof box / fridge / camping.
A8: SUV / truck | B8: Winter studded $2,200 · Summer AT/MT $1,600 · Roof box $1,000 · Fridge $900 · Camping $1,500
A9: Van / family | B9: Winter studded $1,400 · Summer all-season $1,000 · Roof box $1,000 · Fridge $900 · Camping $1,500
A10: Camping pack | B10: Optional add-on — carried on SUVs & vans only. Generates upsell revenue (see below).
A12: TIRE REFRESH (ongoing)
A13: Tire Refresh/Yr | B13: = (Winter + Summer tires) ÷ 3-yr tire life. Funds replacement as studded/perf tires wear.
A14: Applies | B14: Hits BOTH during-loan and post-loan net — tires keep wearing after the car is paid off.
A16: CAMPING UPSELL REVENUE
A17: Camp $/Day | B17: $35/day add-on when a guest rents the camping pack
A18: Camp Attach % | B18: 25% of rental days include the camping pack (SUVs & vans)
A19: Camp Rev/Yr | B19: = Rental Days/Yr × Attach % × Camp $/Day. Added into Gross Revenue.
A21: 5-YEAR OUTPUTS
A22: Residual % | B22: Resale as % of purchase price by type. Porsche/Toyota/Lexus hold value; 356 appreciates (105%); R-Class weakest (60%).
A23: Residual $ (5yr) | B23: = Purchase Price × Residual %
A24: Total Miles (5yr) | B24: = Rental Days/Yr × Avg Miles/Rental Day × 5
A25: 5-Yr Cumulative Profit | B25: = (Net/Yr During Loan × 5) + Residual Value − Down Payment
A27: HOW TO USE
A28: Edit any white cell | B28: Prices, rates, days/mo, kit costs, camp attach %, residual %, miles/day all recalc automatically.
A29: Under-consideration cars | B29: Lexus LX 600, Ineos Grenadier, Mercedes R-Class still "under consideration" — included for comparison.
